cherry_etl/__init__.py
cherry_etl/config.py
cherry_etl/pipeline.py
cherry_etl/utils.py
cherry_etl/steps/__init__.py
cherry_etl/steps/base58_encode.py
cherry_etl/steps/cast.py
cherry_etl/steps/cast_by_type.py
cherry_etl/steps/datafusion_step.py
cherry_etl/steps/evm_decode_events.py
cherry_etl/steps/evm_validate_block_data.py
cherry_etl/steps/glaciers_events.py
cherry_etl/steps/hex_encode.py
cherry_etl/steps/polars_step.py
cherry_etl/steps/set_chain_id.py
cherry_etl/steps/svm_decode_instructions.py
cherry_etl/steps/svm_decode_logs.py
cherry_etl/steps/u256_to_binary.py
cherry_etl/steps/util.py
cherry_etl/writers/__init__.py
cherry_etl/writers/base.py
cherry_etl/writers/clickhouse.py
cherry_etl/writers/delta_lake.py
cherry_etl/writers/duckdb.py
cherry_etl/writers/iceberg.py
cherry_etl/writers/pyarrow_dataset.py
cherry_etl/writers/writer.py
cherry_etl-0.8.0.dist-info/METADATA
cherry_etl-0.8.0.dist-info/WHEEL
cherry_etl-0.8.0.dist-info/licenses/LICENSE-APACHE
cherry_etl-0.8.0.dist-info/licenses/LICENSE-MIT
cherry_etl-0.8.0.dist-info/RECORD
