Metadata-Version: 2.4
Name: cherry-etl
Version: 0.8.0
Summary: Library for building blockchain pipelines
Author-email: Ozgur Akkurt <ozgur@steelcake.com>, Yule Andrade <yule@steelcake.com>
License-Expression: MIT OR Apache-2.0
License-File: LICENSE-APACHE
License-File: LICENSE-MIT
Requires-Python: >=3.11
Requires-Dist: cherry-core>=0.6.1
Requires-Dist: clickhouse-connect>=0.8.15
Requires-Dist: datafusion>=46.0.0
Requires-Dist: deltalake>=0.24.0
Requires-Dist: duckdb>=1.2.1
Requires-Dist: glaciers>=2.0.2
Requires-Dist: polars>=1.25.2
Requires-Dist: psycopg2-binary>=2.9.10
Requires-Dist: pyarrow-stubs>=17.17
Requires-Dist: pyarrow>=19.0.1
Requires-Dist: pyiceberg>=0.8.1
Requires-Dist: sqlalchemy>=2.0.38
